waflabs/__init__.py
waflabs/waflabsapi/__init__.py
waflabs/waflabsapi/waflabsapi.py
waflabs-1.0.3.data/scripts/waflabs
waflabs-1.0.3.dist-info/LICENSE
waflabs-1.0.3.dist-info/METADATA
waflabs-1.0.3.dist-info/WHEEL
waflabs-1.0.3.dist-info/top_level.txt
waflabs-1.0.3.dist-info/RECORD
