Metadata-Version: 2.1
Name: waflabs
Version: 1.0.3
Summary: A python CLI and wrapper for the WAFLABS API - https://waflabs.com/api/
Home-page: https://waflabs.com
Author: waflabs
Author-email: UNKNOWN
License: MIT
Keywords: wrapper library waf lab labs waflabs api cli
Platform: UNKNOWN
Classifier: Intended Audience :: Developers
Classifier: Topic :: Software Development :: Libraries :: Python Modules
Classifier: Programming Language :: Python :: 2.7
Classifier: License :: OSI Approved :: MIT License
Requires-Dist: requests
Requires-Dist: pyopenssl
Requires-Dist: html
Requires-Dist: yaspin
